rupdf-0.1.7.dist-info/METADATA
rupdf-0.1.7.dist-info/WHEEL
rupdf-0.1.7.dist-info/licenses/LICENSE
rupdf/__init__.py
rupdf/__init__.pyi
rupdf/_rupdf.cpython-312-darwin.so
rupdf/_rupdf.pyi
rupdf/py.typed
rupdf-0.1.7.dist-info/RECORD
