Metadata-Version: 2.4
Name: rupdf
Version: 0.1.7
Classifier: Development Status :: 4 - Beta
Classifier: Intended Audience :: Developers
Classifier: License :: OSI Approved :: MIT License
Classifier: Programming Language :: Python :: 3.11
Classifier: Programming Language :: Python :: 3.12
Classifier: Programming Language :: Python :: 3.13
Classifier: Programming Language :: Rust
Classifier: Topic :: Multimedia :: Graphics :: Graphics Conversion
Requires-Dist: pytest>=7.0 ; extra == 'dev'
Requires-Dist: reportlab>=4.0 ; extra == 'dev'
Provides-Extra: dev
License-File: LICENSE
Summary: A fast, minimal PDF page renderer
Home-Page: https://github.com/stringking/rupdf
License-Expression: MIT
Requires-Python: >=3.11
Project-URL: Repository, https://github.com/stringking/rupdf
Project-URL: Issues, https://github.com/stringking/rupdf/issues
